pyichtankebillig
